<annotation>
	<folder>JPEGImages</folder>
	<filename>361_2(3).jpg</filename>
	<path>D:\Zhe_project\logo_detection\VOCdevkit\VOC2007\JPEGImages\361_2(3).jpg</path>
	<source>
		<database>Unknown</database>
	</source>
	<size>
		<width>800</width>
		<height>800</height>
		<depth>3</depth>
	</size>
	<segmented>0</segmented>
	<object>
		<name>361</name>
		<pose>Unspecified</pose>
		<truncated>0</truncated>
		<difficult>0</difficult>
		<bndbox>
			<xmin>200</xmin>
			<ymin>59</ymin>
			<xmax>320</xmax>
			<ymax>155</ymax>
		</bndbox>
	</object>
	<object>
		<name>361</name>
		<pose>Unspecified</pose>
		<truncated>0</truncated>
		<difficult>0</difficult>
		<bndbox>
			<xmin>241</xmin>
			<ymin>385</ymin>
			<xmax>294</xmax>
			<ymax>447</ymax>
		</bndbox>
	</object>
	<object>
		<name>361</name>
		<pose>Unspecified</pose>
		<truncated>0</truncated>
		<difficult>0</difficult>
		<bndbox>
			<xmin>586</xmin>
			<ymin>528</ymin>
			<xmax>650</xmax>
			<ymax>589</ymax>
		</bndbox>
	</object>
</annotation>
