<annotation>
	<folder>JPEGImages</folder>
	<filename>anta_0(177).jpg</filename>
	<path>D:\Zhe_project\logo_detection\VOCdevkit\VOC2007\JPEGImages\anta_0(177).jpg</path>
	<source>
		<database>Unknown</database>
	</source>
	<size>
		<width>800</width>
		<height>800</height>
		<depth>3</depth>
	</size>
	<segmented>0</segmented>
	<object>
		<name>anta</name>
		<pose>Unspecified</pose>
		<truncated>0</truncated>
		<difficult>0</difficult>
		<bndbox>
			<xmin>218</xmin>
			<ymin>445</ymin>
			<xmax>374</xmax>
			<ymax>537</ymax>
		</bndbox>
	</object>
	<object>
		<name>anta</name>
		<pose>Unspecified</pose>
		<truncated>0</truncated>
		<difficult>0</difficult>
		<bndbox>
			<xmin>44</xmin>
			<ymin>23</ymin>
			<xmax>224</xmax>
			<ymax>144</ymax>
		</bndbox>
	</object>
</annotation>
