<annotation>
	<folder>kappa</folder>
	<filename>kappa_132.jpg</filename>
	<path>C:\Users\Cui\Desktop\kappa\kappa_132.jpg</path>
	<source>
		<database>Unknown</database>
	</source>
	<size>
		<width>2640</width>
		<height>4048</height>
		<depth>3</depth>
	</size>
	<segmented>0</segmented>
	<object>
		<name>kappa</name>
		<pose>Unspecified</pose>
		<truncated>0</truncated>
		<difficult>0</difficult>
		<bndbox>
			<xmin>1067</xmin>
			<ymin>726</ymin>
			<xmax>1281</xmax>
			<ymax>871</ymax>
		</bndbox>
	</object>
</annotation>
