<annotation>
	<folder>kappa</folder>
	<filename>kappa_43.jpg</filename>
	<path>C:\Users\Cui\Desktop\kappa\kappa_43.jpg</path>
	<source>
		<database>Unknown</database>
	</source>
	<size>
		<width>400</width>
		<height>309</height>
		<depth>3</depth>
	</size>
	<segmented>0</segmented>
	<object>
		<name>kappa</name>
		<pose>Unspecified</pose>
		<truncated>0</truncated>
		<difficult>0</difficult>
		<bndbox>
			<xmin>78</xmin>
			<ymin>104</ymin>
			<xmax>135</xmax>
			<ymax>171</ymax>
		</bndbox>
	</object>
	<object>
		<name>kappa</name>
		<pose>Unspecified</pose>
		<truncated>0</truncated>
		<difficult>0</difficult>
		<bndbox>
			<xmin>208</xmin>
			<ymin>69</ymin>
			<xmax>281</xmax>
			<ymax>109</ymax>
		</bndbox>
	</object>
</annotation>
