<annotation>
	<folder>JPEGImages</folder>
	<filename>Nike_55.jpg</filename>
	<path>D:\Zhe_project\logo_detection\VOCdevkit\VOC2007\JPEGImages\Nike_55.jpg</path>
	<source>
		<database>Unknown</database>
	</source>
	<size>
		<width>500</width>
		<height>832</height>
		<depth>3</depth>
	</size>
	<segmented>0</segmented>
	<object>
		<name>nike</name>
		<pose>Unspecified</pose>
		<truncated>0</truncated>
		<difficult>0</difficult>
		<bndbox>
			<xmin>252</xmin>
			<ymin>272</ymin>
			<xmax>336</xmax>
			<ymax>395</ymax>
		</bndbox>
	</object>
</annotation>